im_jax/__init__.py
im_jax/bicubic.py
im_jax/boundary.py
im_jax/kernels.py
im_jax/utils.py
im_jax-0.1.1.dist-info/licenses/LICENSE
im_jax-0.1.1.dist-info/METADATA
im_jax-0.1.1.dist-info/WHEEL
im_jax-0.1.1.dist-info/top_level.txt
im_jax-0.1.1.dist-info/RECORD
